nonebot_plugin_logo/__init__.py
nonebot_plugin_logo/data_source.py
nonebot_plugin_logo/templates/5000choyen.html
nonebot_plugin_logo/templates/douyin.html
nonebot_plugin_logo/templates/fontfaceobserver.js
nonebot_plugin_logo/templates/fonts/NotoSansSC-Regular.otf
nonebot_plugin_logo/templates/fonts/NotoSerifSC-Regular.otf
nonebot_plugin_logo/templates/fonts/Product Sans Regular.ttf
nonebot_plugin_logo/templates/google.html
nonebot_plugin_logo/templates/images/corner.png
nonebot_plugin_logo/templates/pornhub.html
nonebot_plugin_logo/templates/youtube.html
nonebot_plugin_logo-0.2.2.dist-info/LICENSE
nonebot_plugin_logo-0.2.2.dist-info/WHEEL
nonebot_plugin_logo-0.2.2.dist-info/METADATA
nonebot_plugin_logo-0.2.2.dist-info/RECORD
