Metadata-Version: 2.1
Name: nonebot-plugin-logo
Version: 0.2.2
Summary: Nonebot2插件，用于制作 PornHub 等风格 logo
Home-page: https://github.com/noneplugin/nonebot-plugin-logo
License: MIT
Author: meetwq
Author-email: meetwq@gmail.com
Requires-Python: >=3.7.3,<4.0.0
Classifier: License :: OSI Approved :: MIT License
Classifier: Programming Language :: Python :: 3
Classifier: Programming Language :: Python :: 3.10
Classifier: Programming Language :: Python :: 3.8
Classifier: Programming Language :: Python :: 3.9
Requires-Dist: Jinja2 (>=3.0.0,<4.0.0)
Requires-Dist: imageio (>=2.12.0,<3.0.0)
Requires-Dist: nonebot-adapter-onebot (>=2.0.0-beta.1,<3.0.0)
Requires-Dist: nonebot-plugin-htmlrender (>=0.0.4.1)
Requires-Dist: nonebot2 (>=2.0.0-beta.4,<3.0.0)
Project-URL: Repository, https://github.com/noneplugin/nonebot-plugin-logo
